<?xml version="1.0" encoding="UTF-8" standalone="no"?><Tickets><Ticket><Id>100</Id><Date>16.05.2017</Date><Places>11010100000000000000000000000000000000000000000000000000000000000010000000000000000000000000000</Places><PiP>Курченко Игорь Дмитриевич#EP123451!2|Паршин Александр Юрьевич#EP123456!4|Паршин Олександ Юрьевич#EP234567!67|Паршин Олександр Юрьевич#AA123456!6|Паршин Олександр Юрьевич#УК123456!1|</PiP></Ticket><Ticket><Id>101</Id><Date>16.05.2017</Date><Places>0100000000000000</Places><PiP>Курченко Игорь Дмитриевич#EP123451!2|</PiP></Ticket><Ticket><Id>102</Id><Date>16.05.2017</Date><Places>0010000000000000</Places><PiP>Курченко Игорь Дмитриевич#EP123451!3|</PiP></Ticket><Ticket><Id>103</Id><Date>16.05.2017</Date><Places>0010000000000000</Places><PiP>Курченко Игорь Дмитриевич#EP123451!3|</PiP></Ticket></Tickets>